mhsa/__init__.py
mhsa/algorithms/__init__.py
mhsa/algorithms/fa.py
mhsa/algorithms/pso.py
mhsa/diversity_metrics/__init__.py
mhsa/diversity_metrics/individual_diversity/__init__.py
mhsa/diversity_metrics/individual_diversity/idt.py
mhsa/diversity_metrics/individual_diversity/ifiqr.py
mhsa/diversity_metrics/individual_diversity/ifm.py
mhsa/diversity_metrics/individual_diversity/isi.py
mhsa/diversity_metrics/population_diversity/__init__.py
mhsa/diversity_metrics/population_diversity/aad.py
mhsa/diversity_metrics/population_diversity/dpc.py
mhsa/diversity_metrics/population_diversity/fdc.py
mhsa/diversity_metrics/population_diversity/pdi.py
mhsa/diversity_metrics/population_diversity/ped.py
mhsa/diversity_metrics/population_diversity/pfm.py
mhsa/diversity_metrics/population_diversity/pfsd.py
mhsa/diversity_metrics/population_diversity/pmd.py
mhsa/tools/__init__.py
mhsa/tools/meta_ga.py
mhsa/tools/metaheuristics_similarity_analyzer.py
mhsa/tools/optimization_data.py
mhsa/tools/optimization_tools.py
mhsa/util/__init__.py
mhsa/util/helper.py
mhsa-1.1.0.dist-info/LICENSE
mhsa-1.1.0.dist-info/METADATA
mhsa-1.1.0.dist-info/WHEEL
mhsa-1.1.0.dist-info/RECORD
