Metadata-Version: 2.3
Name: mhsa
Version: 1.1.0
Summary: MHSA - Metaheuristics Similarity Analyzer
License: MIT
Author: hozjan
Requires-Python: >=3.10,<3.14
Classifier: License :: OSI Approved :: MIT License
Classifier: Programming Language :: Python :: 3
Classifier: Programming Language :: Python :: 3.10
Classifier: Programming Language :: Python :: 3.11
Classifier: Programming Language :: Python :: 3.12
Classifier: Programming Language :: Python :: 3.13
Requires-Dist: cloudpickle (>=3.0.0,<4.0.0)
Requires-Dist: graphviz (>=0.20.3,<0.21.0)
Requires-Dist: matplotlib (>=3.10.5,<4.0.0)
Requires-Dist: niapy (>=2.5.2,<3.0.0)
Requires-Dist: numba (>=0.60.0,<0.61.0)
Requires-Dist: numpy (>=1.26.1,<2.0.0)
Requires-Dist: pandas (>=2.2.1,<3.0.0)
Requires-Dist: pygad (>=3.5.0,<4.0.0)
Requires-Dist: pylatex (>=1.4.2,<2.0.0)
Requires-Dist: pyqt6 (>=6.9.1,<7.0.0)
Requires-Dist: scikit-learn (>=1.4.1.post1,<2.0.0)
Requires-Dist: seaborn (>=0.13.2,<0.14.0)
